ottoanime/__init__.py
ottoanime/ottoanime.py
ottoanime-0.0.2.dist-info/LICENSE
ottoanime-0.0.2.dist-info/METADATA
ottoanime-0.0.2.dist-info/WHEEL
ottoanime-0.0.2.dist-info/top_level.txt
ottoanime-0.0.2.dist-info/RECORD
